gps2space/__init__.py
gps2space/dist.py
gps2space/geodf.py
gps2space/space.py
gps2space-0.2.1.dist-info/LICENSE
gps2space-0.2.1.dist-info/METADATA
gps2space-0.2.1.dist-info/WHEEL
gps2space-0.2.1.dist-info/top_level.txt
gps2space-0.2.1.dist-info/RECORD
